{
    "data": [
        {
            "cusip": "912795S36",
            "bid_price": 99.999667,
            "offer_price": 0.0,
            "mid_price": 49.9998335,
            "eod_price": 99.999833,
            "bid_yield": 0.12258175874347742,
            "offer_yield": null,
            "eod_yield": 0.06146549911404826
        },
        {
            "cusip": "912795P54",
            "bid_price": 99.9995,
            "offer_price": 99.999625,
            "mid_price": 99.9995625,
            "eod_price": 99.999556,
            "bid_yield": 0.02287637158730598,
            "offer_yield": 0.017157024259008672,
            "eod_yield": 0.020314082878402445
        },
        {
            "cusip": "912795P62",
            "bid_price": 99.998222,
            "offer_price": 99.998444,
            "mid_price": 99.998333,
            "eod_price": 99.999583,
            "bid_yield": 0.04338829877213327,
            "offer_yield": 0.037970306748963005,
            "eod_yield": 0.010175087772649374
        },
        {
            "cusip": "912795P70",
            "bid_price": 99.997444,
            "offer_price": 99.997764,
            "mid_price": 99.997604,
            "eod_price": 99.998167,
            "bid_yield": 0.04252761879388351,
            "offer_yield": 0.03720279377166072,
            "eod_yield": 0.030497068152156116
        },
        {
            "cusip": "912795S44",
            "bid_price": 99.995833,
            "offer_price": 99.99625,
            "mid_price": 99.9960415,
            "eod_price": 99.995972,
            "bid_yield": 0.05259843557731635,
            "offer_yield": 0.047334084857791336,
            "eod_yield": 0.05084363417245505
        },
        {
            "cusip": "912795P96",
            "bid_price": 99.993833,
            "offer_price": 99.994347,
            "mid_price": 99.99409,
            "eod_price": 99.994,
            "bid_yield": 0.06270959587942274,
            "offer_yield": 0.057482050061328734,
            "eod_yield": 0.061011134077342134
        },
        {
            "cusip": "912795Q20",
            "bid_price": 99.993889,
            "offer_price": 99.9945,
            "mid_price": 99.99419449999999,
            "eod_price": 99.994028,
            "bid_yield": 0.05230722767514912,
            "offer_yield": 0.0470766015546904,
            "eod_yield": 0.05111726680863287
        },
        {
            "cusip": "912795Q38",
            "bid_price": 99.9915,
            "offer_price": 99.992208,
            "mid_price": 99.991854,
            "eod_price": 99.991667,
            "bid_yield": 0.06257244518679246,
            "offer_yield": 0.05735957816841354,
            "eod_yield": 0.0613428409302488
        },
        {
            "cusip": "912795S51",
            "bid_price": 99.990333,
            "offer_price": 99.991139,
            "mid_price": 99.990736,
            "eod_price": 99.9905,
            "bid_yield": 0.062424265572209835,
            "offer_yield": 0.057218577746346116,
            "eod_yield": 0.061345653150736985
        },
        {
            "cusip": "912795Q53",
            "bid_price": 99.992667,
            "offer_price": 99.993583,
            "mid_price": 99.99312499999999,
            "eod_price": 99.990972,
            "bid_yield": 0.04152189337190004,
            "offer_yield": 0.0363345581091539,
            "eod_yield": 0.05112120891384237
        },
        {
            "cusip": "912795Q61",
            "bid_price": 99.988,
            "offer_price": 99.989,
            "mid_price": 99.9885,
            "eod_price": 99.988167,
            "bid_yield": 0.061872435298072785,
            "offer_yield": 0.05671538438029447,
            "eod_yield": 0.061011194960811206
        },
        {
            "cusip": "912795R37",
            "bid_price": 99.984639,
            "offer_price": 99.985736,
            "mid_price": 99.9851875,
            "eod_price": 99.984833,
            "bid_yield": 0.07209706686612957,
            "offer_yield": 0.06694705317147827,
            "eod_yield": 0.07118629407365257
        },
        {
            "cusip": "912795S69",
            "bid_price": 99.9785,
            "offer_price": 99.979694,
            "mid_price": 99.979097,
            "eod_price": 99.97875,
            "bid_yield": 0.09260785790764856,
            "offer_yield": 0.08746324453546102,
            "eod_yield": 0.09153066151942031
        },
        {
            "cusip": "912795R52",
            "bid_price": 99.974167,
            "offer_price": 99.975458,
            "mid_price": 99.9748125,
            "eod_price": 99.974444,
            "bid_yield": 0.10281010541257896,
            "offer_yield": 0.09767030190637703,
            "eod_yield": 0.10170728035202647
        },
        {
            "cusip": "912795R60",
            "bid_price": 99.969444,
            "offer_price": 99.970833,
            "mid_price": 99.97013849999999,
            "eod_price": 99.96975,
            "bid_yield": 0.11363152365446864,
            "offer_yield": 0.10846396224655268,
            "eod_yield": 0.11249307997177739
        },
        {
            "cusip": "912795R78",
            "bid_price": 99.976222,
            "offer_price": 99.976222,
            "mid_price": 99.976222,
            "eod_price": 99.9735,
            "bid_yield": 0.0825768963344516,
            "offer_yield": 0.0825768963344516,
            "eod_yield": 0.09203336100893926
        },
        {
            "cusip": "912795R86",
            "bid_price": 99.9715,
            "offer_price": 99.973083,
            "mid_price": 99.97229150000001,
            "eod_price": 99.97175,
            "bid_yield": 0.09284893346627959,
            "offer_yield": 0.08768992053392788,
            "eod_yield": 0.09203416667343149
        },
        {
            "cusip": "912795R94",
            "bid_price": 99.966389,
            "offer_price": 99.968069,
            "mid_price": 99.967229,
            "eod_price": 99.963333,
            "bid_yield": 0.10311763325390662,
            "offer_yield": 0.09796135359233263,
            "eod_yield": 0.11249771437683893
        },
        {
            "cusip": "912795S77",
            "bid_price": 99.964444,
            "offer_price": 99.964444,
            "mid_price": 99.964444,
            "eod_price": 99.961194,
            "bid_yield": 0.1030732813136589,
            "offer_yield": 0.1030732813136589,
            "eod_yield": 0.1124991840809812
        },
        {
            "cusip": "912795S85",
            "bid_price": 99.95125,
            "offer_price": 99.953125,
            "mid_price": 99.95218750000001,
            "eod_price": 99.951611,
            "bid_yield": 0.13395808291816236,
            "offer_yield": 0.12880298184570815,
            "eod_yield": 0.13296553628595661
        },
        {
            "cusip": "912795T27",
            "bid_price": 99.940833,
            "offer_price": 99.942806,
            "mid_price": 99.94181950000001,
            "eod_price": 99.937333,
            "bid_yield": 0.1545270409069995,
            "offer_yield": 0.14937073865322867,
            "eod_yield": 0.1636746318506364
        },
        {
            "cusip": "912795T35",
            "bid_price": 99.933778,
            "offer_price": 99.933778,
            "mid_price": 99.933778,
            "eod_price": 99.934222,
            "bid_yield": 0.1647824987143913,
            "offer_yield": 0.1647824987143913,
            "eod_yield": 0.16367686244660254
        },
        {
            "cusip": "912795T43",
            "bid_price": 99.926333,
            "offer_price": 99.926333,
            "mid_price": 99.926333,
            "eod_price": 99.9225,
            "bid_yield": 0.17504072294519374,
            "offer_yield": 0.17504072294519374,
            "eod_yield": 0.18415606849485344
        },
        {
            "cusip": "912795T50",
            "bid_price": 99.9185,
            "offer_price": 99.9185,
            "mid_price": 99.9185,
            "eod_price": 99.9145,
            "bid_yield": 0.18227454668542165,
            "offer_yield": 0.18227454668542165,
            "eod_yield": 0.19122864114126512
        },
        {
            "cusip": "912795T68",
            "bid_price": 99.915,
            "offer_price": 99.915,
            "mid_price": 99.915,
            "eod_price": 99.910806,
            "bid_yield": 0.18223140028403614,
            "offer_yield": 0.18223140028403614,
            "eod_yield": 0.19123122408839222
        },
        {
            "cusip": "912795T76",
            "bid_price": 99.906583,
            "offer_price": 99.906583,
            "mid_price": 99.906583,
            "eod_price": 99.902222,
            "bid_yield": 0.19232399863003,
            "offer_yield": 0.19232399863003,
            "eod_yield": 0.20131120131884314
        },
        {
            "cusip": "912795U33",
            "bid_price": 99.89,
            "offer_price": 99.89,
            "mid_price": 99.89,
            "eod_price": 99.885083,
            "bid_yield": 0.20354875876331938,
            "offer_yield": 0.20354875876331938,
            "eod_yield": 0.21265745951767787
        },
        {
            "cusip": "912795U41",
            "bid_price": 99.868167,
            "offer_price": 99.868167,
            "mid_price": 99.868167,
            "eod_price": 99.8625,
            "bid_yield": 0.21303685152001012,
            "offer_yield": 0.21303685152001012,
            "eod_yield": 0.22220588861136162
        },
        {
            "cusip": "912795U58",
            "bid_price": 99.837722,
            "offer_price": 99.837722,
            "mid_price": 99.837722,
            "eod_price": 99.831333,
            "bid_yield": 0.23416056036171531,
            "offer_yield": 0.23416056036171531,
            "eod_yield": 0.24339302553539388
        },
        {
            "cusip": "912795U66",
            "bid_price": 99.757167,
            "offer_price": 99.757167,
            "mid_price": 99.757167,
            "eod_price": 99.758028,
            "bid_yield": 0.3152877650807493,
            "offer_yield": 0.3152877650807493,
            "eod_yield": 0.31416763223025174
        },
        {
            "cusip": "912795U74",
            "bid_price": 99.715833,
            "offer_price": 99.720139,
            "mid_price": 99.717986,
            "eod_price": 99.708167,
            "bid_yield": 0.33593026794900116,
            "offer_yield": 0.33082854261763023,
            "eod_yield": 0.3450137698078713
        },
        {
            "cusip": "912795U82",
            "bid_price": 99.662,
            "offer_price": 99.666694,
            "mid_price": 99.664347,
            "eod_price": 99.663,
            "bid_yield": 0.36679088067551935,
            "offer_yield": 0.3616839216493632,
            "eod_yield": 0.36570287366880927
        },
        {
            "cusip": "912828HD5",
            "bid_price": 100.087432,
            "offer_price": 0.0,
            "mid_price": 50.043716,
            "eod_price": 100.0625,
            "bid_yield": -1.33118505831336,
            "offer_yield": null,
            "eod_yield": 0.16346764199855862
        },
        {
            "cusip": "912828CX6",
            "bid_price": 100.1875,
            "offer_price": 0.0,
            "mid_price": 50.09375,
            "eod_price": 100.1875,
            "bid_yield": 0.10539577977033934,
            "offer_yield": null,
            "eod_yield": 0.10539577977033934
        },
        {
            "cusip": "912828HF0",
            "bid_price": 100.375,
            "offer_price": 0.0,
            "mid_price": 50.1875,
            "eod_price": 100.34375,
            "bid_yield": -0.10283353131047812,
            "offer_yield": 306357356030.04333,
            "eod_yield": 0.20253543894636136
        },
        {
            "cusip": "912828DB3",
            "bid_price": 100.46875,
            "offer_price": 0.0,
            "mid_price": 50.234375,
            "eod_price": 100.46875,
            "bid_yield": 0.17965360069309108,
            "offer_yield": 1135099466.8174982,
            "eod_yield": 0.17965360069309108
        },
        {
            "cusip": "912828FX3",
            "bid_price": 100.65625,
            "offer_price": 0.0,
            "mid_price": 50.328125,
            "eod_price": 100.625,
            "bid_yield": -0.018794976417007846,
            "offer_yield": 431715267.3166148,
            "eod_yield": 0.19748410703947758
        },
        {
            "cusip": "912828HJ2",
            "bid_price": 100.5625,
            "offer_price": 0.0,
            "mid_price": 50.28125,
            "eod_price": 100.5625,
            "bid_yield": 0.034906565824753356,
            "offer_yield": 66035884.78849261,
            "eod_yield": 0.034906565824753356
        },
        {
            "cusip": "912828DE7",
            "bid_price": 100.75,
            "offer_price": 0.0,
            "mid_price": 50.375,
            "eod_price": 100.75,
            "bid_yield": 0.1498985180082641,
            "offer_yield": 6530194.678845866,
            "eod_yield": 0.1498985180082641
        },
        {
            "cusip": "912828HL7",
            "bid_price": 100.84375,
            "offer_price": 0.0,
            "mid_price": 50.421875,
            "eod_price": 100.84375,
            "bid_yield": 0.08035206354249538,
            "offer_yield": 1965781.6718584017,
            "eod_yield": 0.08035206354249538
        },
        {
            "cusip": "912828DG2",
            "bid_price": 101.0625,
            "offer_price": 0.0,
            "mid_price": 50.53125,
            "eod_price": 101.0625,
            "bid_yield": 0.16199459615298437,
            "offer_yield": 665406.4597109029,
            "eod_yield": 0.16199459615298437
        },
        {
            "cusip": "912828HP8",
            "bid_price": 100.6875,
            "offer_price": 0.0,
            "mid_price": 50.34375,
            "eod_price": 100.6875,
            "bid_yield": 0.16214976900659664,
            "offer_yield": 742469.8340721725,
            "eod_yield": 0.16214976900659664
        },
        {
            "cusip": "912828GG9",
            "bid_price": 101.8125,
            "offer_price": 0.0,
            "mid_price": 50.90625,
            "eod_price": 101.78125,
            "bid_yield": 0.11537607386402939,
            "offer_yield": 172166.84028863066,
            "eod_yield": 0.19349189195781852
        },
        {
            "cusip": "9128275Z1",
            "bid_price": 102.46875,
            "offer_price": 0.0,
            "mid_price": 51.234375,
            "eod_price": 102.46875,
            "bid_yield": 0.18511357084010788,
            "offer_yield": 116512.67096602477,
            "eod_yield": 0.18511357084010788
        },
        {
            "cusip": "9128275Z1",
            "bid_price": 102.46875,
            "offer_price": 0.0,
            "mid_price": 51.234375,
            "eod_price": 102.46875,
            "bid_yield": 0.18511357084010788,
            "offer_yield": 116512.67096602477,
            "eod_yield": 0.18511357084010788
        },
        {
            "cusip": "912828DL1",
            "bid_price": 101.3125,
            "offer_price": 0.0,
            "mid_price": 50.65625,
            "eod_price": 101.28125,
            "bid_yield": 0.14341674575584873,
            "offer_yield": 252451.26356473588,
            "eod_yield": 0.2220321947484123
        },
        {
            "cusip": "912828HS2",
            "bid_price": 100.8125,
            "offer_price": 0.0,
            "mid_price": 50.40625,
            "eod_price": 100.78125,
            "bid_yield": 0.104894367388233,
            "offer_yield": 421595.1446500676,
            "eod_yield": 0.17711790338354083
        },
        {
            "cusip": "912828DP2",
            "bid_price": 101.84375,
            "offer_price": 0.0,
            "mid_price": 50.921875,
            "eod_price": 101.78125,
            "bid_yield": 0.11727232810605179,
            "offer_yield": 294641.68830403377,
            "eod_yield": 0.2464625901955206
        },
        {
            "cusip": "912828HU7",
            "bid_price": 100.8125,
            "offer_price": 100.8125,
            "mid_price": 100.8125,
            "eod_price": 100.78125,
            "bid_yield": 0.175163140439252,
            "offer_yield": 0.175163140439252,
            "eod_yield": 0.23526271840610766
        },
        {
            "cusip": "912828DR8",
            "bid_price": 102.09375,
            "offer_price": 102.109375,
            "mid_price": 102.1015625,
            "eod_price": 102.09375,
            "bid_yield": 0.23860970052299166,
            "offer_yield": 0.21111645017248204,
            "eod_yield": 0.23860970052299166
        },
        {
            "cusip": "912828HX1",
            "bid_price": 101.125,
            "offer_price": 101.140625,
            "mid_price": 101.1328125,
            "eod_price": 101.125,
            "bid_yield": 0.24219215745062475,
            "offer_yield": 0.2163333092287049,
            "eod_yield": 0.24219215745062475
        },
        {
            "cusip": "912828GR5",
            "bid_price": 102.71875,
            "offer_price": 102.734375,
            "mid_price": 102.7265625,
            "eod_price": 102.71875,
            "bid_yield": 0.25399602812050126,
            "offer_yield": 0.23021729634143248,
            "eod_yield": 0.25399602812050126
        },
        {
            "cusip": "912828DU1",
            "bid_price": 102.3125,
            "offer_price": 102.328125,
            "mid_price": 102.3203125,
            "eod_price": 102.3125,
            "bid_yield": 0.26324705165772044,
            "offer_yield": 0.23937721389762212,
            "eod_yield": 0.26324705165772044
        },
        {
            "cusip": "912828JA9",
            "bid_price": 101.59375,
            "offer_price": 101.609375,
            "mid_price": 101.6015625,
            "eod_price": 101.5625,
            "bid_yield": 0.28746133948381364,
            "offer_yield": 0.26488732704262247,
            "eod_yield": 0.3326274054170074
        },
        {
            "cusip": "912828DX5",
            "bid_price": 102.40625,
            "offer_price": 102.421875,
            "mid_price": 102.4140625,
            "eod_price": 102.40625,
            "bid_yield": 0.29518888848036623,
            "offer_yield": 0.27403565080246517,
            "eod_yield": 0.29518888848036623
        },
        {
            "cusip": "912828JC5",
            "bid_price": 101.96875,
            "offer_price": 101.96875,
            "mid_price": 101.96875,
            "eod_price": 101.9375,
            "bid_yield": 0.29639021660114867,
            "offer_yield": 0.29639021660114867,
            "eod_yield": 0.33662315827767525
        },
        {
            "cusip": "912828DZ0",
            "bid_price": 102.875,
            "offer_price": 102.890625,
            "mid_price": 102.8828125,
            "eod_price": 102.875,
            "bid_yield": 0.305170209874784,
            "offer_yield": 0.28624150785214664,
            "eod_yield": 0.305170209874784
        },
        {
            "cusip": "912828JF8",
            "bid_price": 102.03125,
            "offer_price": 102.046875,
            "mid_price": 102.0390625,
            "eod_price": 102.03125,
            "bid_yield": 0.35578057730860574,
            "offer_yield": 0.33767554130219235,
            "eod_yield": 0.35578057730860574
        },
        {
            "cusip": "912828ED8",
            "bid_price": 103.34375,
            "offer_price": 103.359375,
            "mid_price": 103.3515625,
            "eod_price": 103.3125,
            "bid_yield": 0.3636252221887754,
            "offer_yield": 0.3465160674094375,
            "eod_yield": 0.39785569342659327
        },
        {
            "cusip": "9128276J6",
            "bid_price": 104.78125,
            "offer_price": 104.796875,
            "mid_price": 104.7890625,
            "eod_price": 104.78125,
            "bid_yield": 0.3713013395664505,
            "offer_yield": 0.35438256091537373,
            "eod_yield": 0.3713013395664505
        },
        {
            "cusip": "9128276J6",
            "bid_price": 104.78125,
            "offer_price": 104.796875,
            "mid_price": 104.7890625,
            "eod_price": 104.78125,
            "bid_yield": 0.3713013395664505,
            "offer_yield": 0.35438256091537373,
            "eod_yield": 0.3713013395664505
        },
        {
            "cusip": "912828JJ0",
            "bid_price": 101.875,
            "offer_price": 101.875,
            "mid_price": 101.875,
            "eod_price": 101.84375,
            "bid_yield": 0.3615258568022445,
            "offer_yield": 0.3615258568022445,
            "eod_yield": 0.39460097239851005
        },
        {
            "cusip": "912828EG1",
            "bid_price": 103.40625,
            "offer_price": 103.421875,
            "mid_price": 103.4140625,
            "eod_price": 103.40625,
            "bid_yield": 0.3722247819489111,
            "offer_yield": 0.35656659469030055,
            "eod_yield": 0.3722247819489111
        },
        {
            "cusip": "912828JL5",
            "bid_price": 101.59375,
            "offer_price": 101.609375,
            "mid_price": 101.6015625,
            "eod_price": 101.59375,
            "bid_yield": 0.4267098851450174,
            "offer_yield": 0.41147008332568236,
            "eod_yield": 0.4267098851450174
        },
        {
            "cusip": "912828EJ5",
            "bid_price": 104.03125,
            "offer_price": 104.046875,
            "mid_price": 104.0390625,
            "eod_price": 104.03125,
            "bid_yield": 0.42467033829615575,
            "offer_yield": 0.4102808769354619,
            "eod_yield": 0.42467033829615575
        },
        {
            "cusip": "912828JP6",
            "bid_price": 101.125,
            "offer_price": 101.125,
            "mid_price": 101.125,
            "eod_price": 101.125,
            "bid_yield": 0.47377019837317774,
            "offer_yield": 0.47377019837317774,
            "eod_yield": 0.47377019837317774
        },
        {
            "cusip": "912828EM8",
            "bid_price": 104.5625,
            "offer_price": 104.578125,
            "mid_price": 104.5703125,
            "eod_price": 104.5625,
            "bid_yield": 0.485943553855826,
            "offer_yield": 0.4726498744693225,
            "eod_yield": 0.485943553855826
        },
        {
            "cusip": "912828JS0",
            "bid_price": 100.875,
            "offer_price": 100.890625,
            "mid_price": 100.8828125,
            "eod_price": 100.875,
            "bid_yield": 0.5064598108841718,
            "offer_yield": 0.49327280232233867,
            "eod_yield": 0.5064598108841718
        },
        {
            "cusip": "912828EQ9",
            "bid_price": 104.6875,
            "offer_price": 104.703125,
            "mid_price": 104.6953125,
            "eod_price": 104.6875,
            "bid_yield": 0.5274716057907902,
            "offer_yield": 0.5150734081111352,
            "eod_yield": 0.5274716057907902
        },
        {
            "cusip": "912828JV3",
            "bid_price": 100.40625,
            "offer_price": 100.40625,
            "mid_price": 100.40625,
            "eod_price": 100.375,
            "bid_yield": 0.5524988501279575,
            "offer_yield": 0.5524988501279575,
            "eod_yield": 0.5772273397890809
        },
        {
            "cusip": "912828ES5",
            "bid_price": 104.78125,
            "offer_price": 104.796875,
            "mid_price": 104.7890625,
            "eod_price": 104.78125,
            "bid_yield": 0.5725058292744178,
            "offer_yield": 0.5608868186108737,
            "eod_yield": 0.5725058292744178
        },
        {
            "cusip": "912828JY7",
            "bid_price": 100.34375,
            "offer_price": 100.359375,
            "mid_price": 100.3515625,
            "eod_price": 100.34375,
            "bid_yield": 0.6189085319996592,
            "offer_yield": 0.6073034119994613,
            "eod_yield": 0.6189085319996592
        },
        {
            "cusip": "9128276T4",
            "bid_price": 106.03125,
            "offer_price": 106.046875,
            "mid_price": 106.0390625,
            "eod_price": 106.03125,
            "bid_yield": 0.6383558559079544,
            "offer_yield": 0.6275123852548171,
            "eod_yield": 0.6383558559079544
        },
        {
            "cusip": "9128276T4",
            "bid_price": 106.03125,
            "offer_price": 106.046875,
            "mid_price": 106.0390625,
            "eod_price": 106.03125,
            "bid_yield": 0.6383558559079544,
            "offer_yield": 0.6275123852548171,
            "eod_yield": 0.6383558559079544
        },
        {
            "cusip": "912828EX4",
            "bid_price": 105.46875,
            "offer_price": 105.484375,
            "mid_price": 105.4765625,
            "eod_price": 105.46875,
            "bid_yield": 0.6425954156519463,
            "offer_yield": 0.6319745474428989,
            "eod_yield": 0.6425954156519463
        },
        {
            "cusip": "912828KE9",
            "bid_price": 100.28125,
            "offer_price": 100.296875,
            "mid_price": 100.2890625,
            "eod_price": 100.28125,
            "bid_yield": 0.6765058193621317,
            "offer_yield": 0.6655051514889486,
            "eod_yield": 0.6765058193621317
        },
        {
            "cusip": "912828KH2",
            "bid_price": 100.25,
            "offer_price": 100.25,
            "mid_price": 100.25,
            "eod_price": 100.25,
            "bid_yield": 0.7089390389363214,
            "offer_yield": 0.7089390389363214,
            "eod_yield": 0.7089390389363214
        },
        {
            "cusip": "912828FA3",
            "bid_price": 106.0625,
            "offer_price": 106.078125,
            "mid_price": 106.0703125,
            "eod_price": 106.0625,
            "bid_yield": 0.7227682035435236,
            "offer_yield": 0.7127942637664747,
            "eod_yield": 0.7227682035435236
        },
        {
            "cusip": "912828FD7",
            "bid_price": 106.53125,
            "offer_price": 106.546875,
            "mid_price": 106.5390625,
            "eod_price": 106.53125,
            "bid_yield": 0.7558733407928048,
            "offer_yield": 0.7464326478343313,
            "eod_yield": 0.7558733407928048
        },
        {
            "cusip": "912828KL3",
            "bid_price": 100.1875,
            "offer_price": 100.1875,
            "mid_price": 100.1875,
            "eod_price": 100.1875,
            "bid_yield": 0.7566773763233351,
            "offer_yield": 0.7566773763233351,
            "eod_yield": 0.7566773763233351
        },
        {
            "cusip": "912828KU3",
            "bid_price": 100.125,
            "offer_price": 100.140625,
            "mid_price": 100.1328125,
            "eod_price": 100.125,
            "bid_yield": 0.7999616019348228,
            "offer_yield": 0.7906066898681138,
            "eod_yield": 0.7999616019348228
        },
        {
            "cusip": "912828FH8",
            "bid_price": 106.8125,
            "offer_price": 106.828125,
            "mid_price": 106.8203125,
            "eod_price": 106.8125,
            "bid_yield": 0.7916142373552127,
            "offer_yield": 0.7826557754224854,
            "eod_yield": 0.7916142373552127
        },
        {
            "cusip": "912828FK1",
            "bid_price": 107.53125,
            "offer_price": 107.546875,
            "mid_price": 107.5390625,
            "eod_price": 107.53125,
            "bid_yield": 0.8177401333505818,
            "offer_yield": 0.8092269137709703,
            "eod_yield": 0.8177401333505818
        },
        {
            "cusip": "912828LF5",
            "bid_price": 100.46875,
            "offer_price": 100.484375,
            "mid_price": 100.4765625,
            "eod_price": 100.46875,
            "bid_yield": 0.8566708333674361,
            "offer_yield": 0.847761820168685,
            "eod_yield": 0.8566708333674361
        },
        {
            "cusip": "912828LG3",
            "bid_price": 100.1875,
            "offer_price": 100.1875,
            "mid_price": 100.1875,
            "eod_price": 100.1875,
            "bid_yield": 0.8974794774364239,
            "offer_yield": 0.8974794774364239,
            "eod_yield": 0.8974794774364239
        },
        {
            "cusip": "912828FN5",
            "bid_price": 107.3125,
            "offer_price": 107.328125,
            "mid_price": 107.3203125,
            "eod_price": 107.3125,
            "bid_yield": 0.8818112249951126,
            "offer_yield": 0.8736663497266067,
            "eod_yield": 0.8818112249951126
        },
        {
            "cusip": "9128277B2",
            "bid_price": 107.6875,
            "offer_price": 107.71875,
            "mid_price": 107.703125,
            "eod_price": 107.6875,
            "bid_yield": 0.8914276667729221,
            "offer_yield": 0.875516859657336,
            "eod_yield": 0.8914276667729221
        },
        {
            "cusip": "9128277B2",
            "bid_price": 107.6875,
            "offer_price": 107.71875,
            "mid_price": 107.703125,
            "eod_price": 107.6875,
            "bid_yield": 0.8914276667729221,
            "offer_yield": 0.875516859657336,
            "eod_yield": 0.8914276667729221
        },
        {
            "cusip": "9128277B2",
            "bid_price": 107.6875,
            "offer_price": 107.71875,
            "mid_price": 107.703125,
            "eod_price": 107.6875,
            "bid_yield": 0.8914276667729221,
            "offer_yield": 0.875516859657336,
            "eod_yield": 0.8914276667729221
        },
        {
            "cusip": "912828FS4",
            "bid_price": 107.03125,
            "offer_price": 107.046875,
            "mid_price": 107.0390625,
            "eod_price": 107.03125,
            "bid_yield": 0.9465354895015454,
            "offer_yield": 0.938713033005223,
            "eod_yield": 0.9465354895015454
        },
        {
            "cusip": "912828LV0",
            "bid_price": 100.0625,
            "offer_price": 100.078125,
            "mid_price": 100.0703125,
            "eod_price": 100.0625,
            "bid_yield": 0.9672247392941213,
            "offer_yield": 0.9590537132936728,
            "eod_yield": 0.9672247392941213
        },
        {
            "cusip": "912828FU9",
            "bid_price": 106.96875,
            "offer_price": 106.984375,
            "mid_price": 106.9765625,
            "eod_price": 106.96875,
            "bid_yield": 1.0001127731234043,
            "offer_yield": 0.9925956219569834,
            "eod_yield": 1.0001127731234043
        },
        {
            "cusip": "912828FW5",
            "bid_price": 107.375,
            "offer_price": 107.40625,
            "mid_price": 107.390625,
            "eod_price": 107.375,
            "bid_yield": 1.0647800005586616,
            "offer_yield": 1.0503673375189468,
            "eod_yield": 1.0647800005586616
        },
        {
            "cusip": "912828JU5",
            "bid_price": 101.375,
            "offer_price": 101.390625,
            "mid_price": 101.3828125,
            "eod_price": 101.375,
            "bid_yield": 1.0982959597196633,
            "offer_yield": 1.0909577183921548,
            "eod_yield": 1.0982959597196633
        },
        {
            "cusip": "912828GA2",
            "bid_price": 107.3125,
            "offer_price": 107.328125,
            "mid_price": 107.3203125,
            "eod_price": 107.3125,
            "bid_yield": 1.0986286420933096,
            "offer_yield": 1.091681221710098,
            "eod_yield": 1.0986286420933096
        },
        {
            "cusip": "912828KA7",
            "bid_price": 99.96875,
            "offer_price": 99.96875,
            "mid_price": 99.96875,
            "eod_price": 99.96875,
            "bid_yield": 1.1390892944882236,
            "offer_yield": 1.1390892944882236,
            "eod_yield": 1.1390892944882236
        },
        {
            "cusip": "912828GC8",
            "bid_price": 107.71875,
            "offer_price": 107.734375,
            "mid_price": 107.7265625,
            "eod_price": 107.75,
            "bid_yield": 1.1633838651657022,
            "offer_yield": 1.1567000622570358,
            "eod_yield": 1.1500174712928775
        },
        {
            "cusip": "912828KB5",
            "bid_price": 99.8125,
            "offer_price": 99.828125,
            "mid_price": 99.8203125,
            "eod_price": 99.84375,
            "bid_yield": 1.207477617160402,
            "offer_yield": 1.200583510857924,
            "eod_yield": 1.1936907258620855
        },
        {
            "cusip": "912828GF1",
            "bid_price": 108.25,
            "offer_price": 108.265625,
            "mid_price": 108.2578125,
            "eod_price": 108.25,
            "bid_yield": 1.1802827519247379,
            "offer_yield": 1.1738512898778424,
            "eod_yield": 1.1802827519247379
        },
        {
            "cusip": "912828KC3",
            "bid_price": 100.3125,
            "offer_price": 100.328125,
            "mid_price": 100.3203125,
            "eod_price": 100.3125,
            "bid_yield": 1.2418089754253472,
            "offer_yield": 1.2351712294317259,
            "eod_yield": 1.2418089754253472
        },
        {
            "cusip": "9128277L0",
            "bid_price": 108.6875,
            "offer_price": 108.703125,
            "mid_price": 108.6953125,
            "eod_price": 108.65625,
            "bid_yield": 1.1793578856697906,
            "offer_yield": 1.1730491681025976,
            "eod_yield": 1.191978702694044
        },
        {
            "cusip": "9128277L0",
            "bid_price": 108.6875,
            "offer_price": 108.703125,
            "mid_price": 108.6953125,
            "eod_price": 108.65625,
            "bid_yield": 1.1793578856697906,
            "offer_yield": 1.1730491681025976,
            "eod_yield": 1.191978702694044
        },
        {
            "cusip": "912828GK0",
            "bid_price": 108.15625,
            "offer_price": 108.171875,
            "mid_price": 108.1640625,
            "eod_price": 108.15625,
            "bid_yield": 1.2071368137982703,
            "offer_yield": 1.200901315111366,
            "eod_yield": 1.2071368137982703
        },
        {
            "cusip": "912828KG4",
            "bid_price": 100.25,
            "offer_price": 100.265625,
            "mid_price": 100.2578125,
            "eod_price": 100.25,
            "bid_yield": 1.2720339573430037,
            "offer_yield": 1.2656117815603118,
            "eod_yield": 1.2720339573430037
        },
        {
            "cusip": "912828GM6",
            "bid_price": 107.96875,
            "offer_price": 107.984375,
            "mid_price": 107.9765625,
            "eod_price": 107.96875,
            "bid_yield": 1.2721559099082038,
            "offer_yield": 1.266118781055208,
            "eod_yield": 1.2721559099082038
        },
        {
            "cusip": "912828KK5",
            "bid_price": 100.15625,
            "offer_price": 100.171875,
            "mid_price": 100.1640625,
            "eod_price": 100.1875,
            "bid_yield": 1.312579604041445,
            "offer_yield": 1.3063535780682338,
            "eod_yield": 1.3001287237281876
        },
        {
            "cusip": "912828GQ7",
            "bid_price": 108.125,
            "offer_price": 108.140625,
            "mid_price": 108.1328125,
            "eod_price": 108.125,
            "bid_yield": 1.308878180279367,
            "offer_yield": 1.3030307435481467,
            "eod_yield": 1.308878180279367
        },
        {
            "cusip": "912828KP4",
            "bid_price": 100.0625,
            "offer_price": 100.078125,
            "mid_price": 100.0703125,
            "eod_price": 100.0625,
            "bid_yield": 1.3506515956544443,
            "offer_yield": 1.3446135181569967,
            "eod_yield": 1.3506515956544443
        },
        {
            "cusip": "912828GU8",
            "bid_price": 108.9375,
            "offer_price": 108.953125,
            "mid_price": 108.9453125,
            "eod_price": 108.9375,
            "bid_yield": 1.3464788317634662,
            "offer_yield": 1.340835478322049,
            "eod_yield": 1.3464788317634662
        },
        {
            "cusip": "912828KX7",
            "bid_price": 101.3125,
            "offer_price": 101.3125,
            "mid_price": 101.3125,
            "eod_price": 101.3125,
            "bid_yield": 1.3820903007367862,
            "offer_yield": 1.3820903007367862,
            "eod_yield": 1.3820903007367862
        },
        {
            "cusip": "912828GW4",
            "bid_price": 109.53125,
            "offer_price": 109.546875,
            "mid_price": 109.5390625,
            "eod_price": 109.53125,
            "bid_yield": 1.350772423131267,
            "offer_yield": 1.3453103437545595,
            "eod_yield": 1.350772423131267
        },
        {
            "cusip": "912828LB4",
            "bid_price": 100.21875,
            "offer_price": 100.234375,
            "mid_price": 100.2265625,
            "eod_price": 100.21875,
            "bid_yield": 1.4200027048283037,
            "offer_yield": 1.4143138590709863,
            "eod_yield": 1.4200027048283037
        },
        {
            "cusip": "912828GZ7",
            "bid_price": 109.0,
            "offer_price": 109.015625,
            "mid_price": 109.0078125,
            "eod_price": 108.96875,
            "bid_yield": 1.3930216548267675,
            "offer_yield": 1.3876990537795613,
            "eod_yield": 1.403669636229869
        },
        {
            "cusip": "912828LH1",
            "bid_price": 100.78125,
            "offer_price": 100.796875,
            "mid_price": 100.7890625,
            "eod_price": 100.78125,
            "bid_yield": 1.4728314082762113,
            "offer_yield": 1.4673182510459055,
            "eod_yield": 1.4728314082762113
        },
        {
            "cusip": "912828AJ9",
            "bid_price": 108.34375,
            "offer_price": 108.375,
            "mid_price": 108.359375,
            "eod_price": 108.34375,
            "bid_yield": 1.4189032284365835,
            "offer_yield": 1.4083605976593363,
            "eod_yield": 1.4189032284365835
        },
        {
            "cusip": "912828HC7",
            "bid_price": 107.65625,
            "offer_price": 107.671875,
            "mid_price": 107.6640625,
            "eod_price": 107.65625,
            "bid_yield": 1.4496121238566622,
            "offer_yield": 1.4443910070009374,
            "eod_yield": 1.4496121238566622
        },
        {
            "cusip": "912828LM0",
            "bid_price": 99.5625,
            "offer_price": 99.578125,
            "mid_price": 99.5703125,
            "eod_price": 99.5625,
            "bid_yield": 1.5259328480761276,
            "offer_yield": 1.5205275389305648,
            "eod_yield": 1.5259328480761276
        },
        {
            "cusip": "912828HE3",
            "bid_price": 108.125,
            "offer_price": 108.140625,
            "mid_price": 108.1328125,
            "eod_price": 108.125,
            "bid_yield": 1.4854360890421114,
            "offer_yield": 1.4803637391044169,
            "eod_yield": 1.4854360890421114
        },
        {
            "cusip": "912828HG8",
            "bid_price": 107.09375,
            "offer_price": 107.109375,
            "mid_price": 107.1015625,
            "eod_price": 107.0625,
            "bid_yield": 1.5235378726119657,
            "offer_yield": 1.5185684355528286,
            "eod_yield": 1.533479351709323
        },
        {
            "cusip": "912828AP5",
            "bid_price": 107.5,
            "offer_price": 107.515625,
            "mid_price": 107.5078125,
            "eod_price": 107.53125,
            "bid_yield": 1.544359774866955,
            "offer_yield": 1.5394627705897876,
            "eod_yield": 1.534566617909386
        },
        {
            "cusip": "912828HK9",
            "bid_price": 105.625,
            "offer_price": 105.640625,
            "mid_price": 105.6328125,
            "eod_price": 105.625,
            "bid_yield": 1.555807062524735,
            "offer_yield": 1.5509184270603562,
            "eod_yield": 1.555807062524735
        },
        {
            "cusip": "912828HM5",
            "bid_price": 106.375,
            "offer_price": 106.390625,
            "mid_price": 106.3828125,
            "eod_price": 106.34375,
            "bid_yield": 1.6129588398128971,
            "offer_yield": 1.6082081163749835,
            "eod_yield": 1.622462775761908
        },
        {
            "cusip": "912828HQ6",
            "bid_price": 103.90625,
            "offer_price": 103.9375,
            "mid_price": 103.921875,
            "eod_price": 103.9375,
            "bid_yield": 1.6709558403992095,
            "offer_yield": 1.6615450790899644,
            "eod_yield": 1.6615450790899644
        },
        {
            "cusip": "912828AU4",
            "bid_price": 107.09375,
            "offer_price": 107.109375,
            "mid_price": 107.1015625,
            "eod_price": 107.125,
            "bid_yield": 1.7125547970931312,
            "offer_yield": 1.7079833318371898,
            "eod_yield": 1.7034126582198448
        },
        {
            "cusip": "912828HT0",
            "bid_price": 103.46875,
            "offer_price": 103.484375,
            "mid_price": 103.4765625,
            "eod_price": 103.46875,
            "bid_yield": 1.7040378720282638,
            "offer_yield": 1.6994215646809252,
            "eod_yield": 1.7040378720282638
        },
        {
            "cusip": "912828HV5",
            "bid_price": 102.5625,
            "offer_price": 102.59375,
            "mid_price": 102.578125,
            "eod_price": 102.5625,
            "bid_yield": 1.7454529380987054,
            "offer_yield": 1.736388638174519,
            "eod_yield": 1.7454529380987054
        },
        {
            "cusip": "912828HY9",
            "bid_price": 104.5625,
            "offer_price": 104.578125,
            "mid_price": 104.5703125,
            "eod_price": 104.5625,
            "bid_yield": 1.809293767437148,
            "offer_yield": 1.8049063328046355,
            "eod_yield": 1.809293767437148
        },
        {
            "cusip": "912828BA7",
            "bid_price": 106.28125,
            "offer_price": 106.3125,
            "mid_price": 106.296875,
            "eod_price": 106.3125,
            "bid_yield": 1.8334088310842576,
            "offer_yield": 1.8248145125904487,
            "eod_yield": 1.8248145125904487
        },
        {
            "cusip": "912828JB7",
            "bid_price": 105.90625,
            "offer_price": 105.921875,
            "mid_price": 105.9140625,
            "eod_price": 105.90625,
            "bid_yield": 1.833751189839748,
            "offer_yield": 1.8294917674313345,
            "eod_yield": 1.833751189839748
        },
        {
            "cusip": "912828JD3",
            "bid_price": 105.4375,
            "offer_price": 105.453125,
            "mid_price": 105.4453125,
            "eod_price": 105.4375,
            "bid_yield": 1.8720076862653272,
            "offer_yield": 1.8678233977387984,
            "eod_yield": 1.8720076862653272
        },
        {
            "cusip": "912828JG6",
            "bid_price": 105.46875,
            "offer_price": 105.484375,
            "mid_price": 105.4765625,
            "eod_price": 105.46875,
            "bid_yield": 1.8951296011258543,
            "offer_yield": 1.8910332756887291,
            "eod_yield": 1.8951296011258543
        },
        {
            "cusip": "912828BH2",
            "bid_price": 108.71875,
            "offer_price": 108.734375,
            "mid_price": 108.7265625,
            "eod_price": 108.71875,
            "bid_yield": 1.9138032021443185,
            "offer_yield": 1.909818862943247,
            "eod_yield": 1.9138032021443185
        },
        {
            "cusip": "912828BH2",
            "bid_price": 108.71875,
            "offer_price": 108.734375,
            "mid_price": 108.7265625,
            "eod_price": 108.71875,
            "bid_yield": 1.9138032021443185,
            "offer_yield": 1.909818862943247,
            "eod_yield": 1.9138032021443185
        },
        {
            "cusip": "912828JK7",
            "bid_price": 104.375,
            "offer_price": 104.390625,
            "mid_price": 104.3828125,
            "eod_price": 104.375,
            "bid_yield": 1.96362779635729,
            "offer_yield": 1.9595836623514076,
            "eod_yield": 1.96362779635729
        },
        {
            "cusip": "912828JM3",
            "bid_price": 104.3125,
            "offer_price": 104.328125,
            "mid_price": 104.3203125,
            "eod_price": 104.3125,
            "bid_yield": 2.0020768932543795,
            "offer_yield": 1.9981075356376368,
            "eod_yield": 2.0020768932543795
        },
        {
            "cusip": "912828JQ4",
            "bid_price": 102.75,
            "offer_price": 102.75,
            "mid_price": 102.75,
            "eod_price": 102.75,
            "bid_yield": 2.047103744584612,
            "offer_yield": 2.047103744584612,
            "eod_yield": 2.047103744584612
        },
        {
            "cusip": "912828BR0",
            "bid_price": 108.65625,
            "offer_price": 108.6875,
            "mid_price": 108.671875,
            "eod_price": 108.6875,
            "bid_yield": 2.05814375483085,
            "offer_yield": 2.0506108528599425,
            "eod_yield": 2.0506108528599425
        },
        {
            "cusip": "912828BR0",
            "bid_price": 108.65625,
            "offer_price": 108.6875,
            "mid_price": 108.671875,
            "eod_price": 108.6875,
            "bid_yield": 2.05814375483085,
            "offer_yield": 2.0506108528599425,
            "eod_yield": 2.0506108528599425
        },
        {
            "cusip": "912828JT8",
            "bid_price": 99.625,
            "offer_price": 99.640625,
            "mid_price": 99.6328125,
            "eod_price": 99.65625,
            "bid_yield": 2.093817315439772,
            "offer_yield": 2.0898881326745373,
            "eod_yield": 2.085959656303471
        },
        {
            "cusip": "912828JW1",
            "bid_price": 97.4375,
            "offer_price": 97.453125,
            "mid_price": 97.4453125,
            "eod_price": 97.46875,
            "bid_yield": 2.1313067473341074,
            "offer_yield": 2.127399230389585,
            "eod_yield": 2.123492426490714
        },
        {
            "cusip": "912828JZ4",
            "bid_price": 98.21875,
            "offer_price": 98.234375,
            "mid_price": 98.2265625,
            "eod_price": 98.21875,
            "bid_yield": 2.1811508717099946,
            "offer_yield": 2.1773285103255167,
            "eod_yield": 2.1811508717099946
        },
        {
            "cusip": "912828CA6",
            "bid_price": 107.625,
            "offer_price": 107.65625,
            "mid_price": 107.640625,
            "eod_price": 107.65625,
            "bid_yield": 2.169744080844559,
            "offer_yield": 2.162561171536206,
            "eod_yield": 2.162561171536206
        },
        {
            "cusip": "912828CA6",
            "bid_price": 107.625,
            "offer_price": 107.65625,
            "mid_price": 107.640625,
            "eod_price": 107.65625,
            "bid_yield": 2.169744080844559,
            "offer_yield": 2.162561171536206,
            "eod_yield": 2.162561171536206
        },
        {
            "cusip": "912828KF6",
            "bid_price": 98.5625,
            "offer_price": 98.578125,
            "mid_price": 98.5703125,
            "eod_price": 98.5625,
            "bid_yield": 2.2175801829919313,
            "offer_yield": 2.21382451263052,
            "eod_yield": 2.2175801829919313
        },
        {
            "cusip": "912828KJ8",
            "bid_price": 97.84375,
            "offer_price": 97.859375,
            "mid_price": 97.8515625,
            "eod_price": 97.84375,
            "bid_yield": 2.2547968973358445,
            "offer_yield": 2.2510934037406423,
            "eod_yield": 2.2547968973358445
        },
        {
            "cusip": "912828KN9",
            "bid_price": 98.1875,
            "offer_price": 98.203125,
            "mid_price": 98.1953125,
            "eod_price": 98.21875,
            "bid_yield": 2.29235946436404,
            "offer_yield": 2.2887228355080076,
            "eod_yield": 2.28508686453849
        },
        {
            "cusip": "912828CJ7",
            "bid_price": 110.875,
            "offer_price": 110.90625,
            "mid_price": 110.890625,
            "eod_price": 110.875,
            "bid_yield": 2.2675808771077444,
            "offer_yield": 2.2608691862033425,
            "eod_yield": 2.2675808771077444
        },
        {
            "cusip": "912828CJ7",
            "bid_price": 110.875,
            "offer_price": 110.90625,
            "mid_price": 110.890625,
            "eod_price": 110.875,
            "bid_yield": 2.2675808771077444,
            "offer_yield": 2.2608691862033425,
            "eod_yield": 2.2675808771077444
        },
        {
            "cusip": "912828KV1",
            "bid_price": 99.6875,
            "offer_price": 99.6875,
            "mid_price": 99.6875,
            "eod_price": 99.6875,
            "bid_yield": 2.3204717405346016,
            "offer_yield": 2.3204717405346016,
            "eod_yield": 2.3204717405346016
        },
        {
            "cusip": "912828KY5",
            "bid_price": 101.1875,
            "offer_price": 101.203125,
            "mid_price": 101.1953125,
            "eod_price": 101.21875,
            "bid_yield": 2.3596222293251743,
            "offer_yield": 2.3561604802933145,
            "eod_yield": 2.352699343166892
        },
        {
            "cusip": "912828LC2",
            "bid_price": 101.0625,
            "offer_price": 101.0625,
            "mid_price": 101.0625,
            "eod_price": 101.0625,
            "bid_yield": 2.3913387221065188,
            "offer_yield": 2.3913387221065188,
            "eod_yield": 2.3913387221065188
        },
        {
            "cusip": "912828CT5",
            "bid_price": 108.65625,
            "offer_price": 108.671875,
            "mid_price": 108.6640625,
            "eod_price": 108.65625,
            "bid_yield": 2.3650486389481506,
            "offer_yield": 2.3618078912901725,
            "eod_yield": 2.3650486389481506
        },
        {
            "cusip": "912828CT5",
            "bid_price": 108.65625,
            "offer_price": 108.671875,
            "mid_price": 108.6640625,
            "eod_price": 108.65625,
            "bid_yield": 2.3650486389481506,
            "offer_yield": 2.3618078912901725,
            "eod_yield": 2.3650486389481506
        },
        {
            "cusip": "912828LK4",
            "bid_price": 99.78125,
            "offer_price": 99.796875,
            "mid_price": 99.7890625,
            "eod_price": 99.78125,
            "bid_yield": 2.4221299661384808,
            "offer_yield": 2.418747203964079,
            "eod_yield": 2.4221299661384808
        },
        {
            "cusip": "912828DC1",
            "bid_price": 108.5625,
            "offer_price": 108.59375,
            "mid_price": 108.578125,
            "eod_price": 108.5625,
            "bid_yield": 2.465978601695127,
            "offer_yield": 2.459774594779449,
            "eod_yield": 2.465978601695127
        },
        {
            "cusip": "912828DC1",
            "bid_price": 108.5625,
            "offer_price": 108.59375,
            "mid_price": 108.578125,
            "eod_price": 108.5625,
            "bid_yield": 2.465978601695127,
            "offer_yield": 2.459774594779449,
            "eod_yield": 2.465978601695127
        },
        {
            "cusip": "912828DM9",
            "bid_price": 107.0625,
            "offer_price": 107.078125,
            "mid_price": 107.0703125,
            "eod_price": 107.0625,
            "bid_yield": 2.5876408424059227,
            "offer_yield": 2.584638610589768,
            "eod_yield": 2.5876408424059227
        },
        {
            "cusip": "912828DM9",
            "bid_price": 107.0625,
            "offer_price": 107.078125,
            "mid_price": 107.0703125,
            "eod_price": 107.0625,
            "bid_yield": 2.5876408424059227,
            "offer_yield": 2.584638610589768,
            "eod_yield": 2.5876408424059227
        },
        {
            "cusip": "912828DM9",
            "bid_price": 107.0625,
            "offer_price": 107.078125,
            "mid_price": 107.0703125,
            "eod_price": 107.0625,
            "bid_yield": 2.5876408424059227,
            "offer_yield": 2.584638610589768,
            "eod_yield": 2.5876408424059227
        },
        {
            "cusip": "912828DV9",
            "bid_price": 107.5625,
            "offer_price": 107.578125,
            "mid_price": 107.5703125,
            "eod_price": 107.5625,
            "bid_yield": 2.671441109331504,
            "offer_yield": 2.6685636721676533,
            "eod_yield": 2.671441109331504
        },
        {
            "cusip": "912828DV9",
            "bid_price": 107.5625,
            "offer_price": 107.578125,
            "mid_price": 107.5703125,
            "eod_price": 107.5625,
            "bid_yield": 2.671441109331504,
            "offer_yield": 2.6685636721676533,
            "eod_yield": 2.671441109331504
        },
        {
            "cusip": "912828DV9",
            "bid_price": 107.5625,
            "offer_price": 107.578125,
            "mid_price": 107.5703125,
            "eod_price": 107.5625,
            "bid_yield": 2.671441109331504,
            "offer_yield": 2.6685636721676533,
            "eod_yield": 2.671441109331504
        },
        {
            "cusip": "912828EE6",
            "bid_price": 108.125,
            "offer_price": 108.140625,
            "mid_price": 108.1328125,
            "eod_price": 108.09375,
            "bid_yield": 2.746386622189823,
            "offer_yield": 2.743624353136242,
            "eod_yield": 2.7519125513620737
        },
        {
            "cusip": "912828EE6",
            "bid_price": 108.125,
            "offer_price": 108.140625,
            "mid_price": 108.1328125,
            "eod_price": 108.09375,
            "bid_yield": 2.746386622189823,
            "offer_yield": 2.743624353136242,
            "eod_yield": 2.7519125513620737
        },
        {
            "cusip": "912828EE6",
            "bid_price": 108.125,
            "offer_price": 108.140625,
            "mid_price": 108.1328125,
            "eod_price": 108.09375,
            "bid_yield": 2.746386622189823,
            "offer_yield": 2.743624353136242,
            "eod_yield": 2.7519125513620737
        },
        {
            "cusip": "912828EN6",
            "bid_price": 109.46875,
            "offer_price": 109.5,
            "mid_price": 109.484375,
            "eod_price": 109.5,
            "bid_yield": 2.809978767096899,
            "offer_yield": 2.8046900208416594,
            "eod_yield": 2.8046900208416594
        },
        {
            "cusip": "912828EN6",
            "bid_price": 109.46875,
            "offer_price": 109.5,
            "mid_price": 109.484375,
            "eod_price": 109.5,
            "bid_yield": 2.809978767096899,
            "offer_yield": 2.8046900208416594,
            "eod_yield": 2.8046900208416594
        },
        {
            "cusip": "912828EW6",
            "bid_price": 109.3125,
            "offer_price": 109.34375,
            "mid_price": 109.328125,
            "eod_price": 109.34375,
            "bid_yield": 2.89312464405014,
            "offer_yield": 2.888007188992315,
            "eod_yield": 2.888007188992315
        },
        {
            "cusip": "912828EW6",
            "bid_price": 109.3125,
            "offer_price": 109.34375,
            "mid_price": 109.328125,
            "eod_price": 109.34375,
            "bid_yield": 2.89312464405014,
            "offer_yield": 2.888007188992315,
            "eod_yield": 2.888007188992315
        },
        {
            "cusip": "912828KS8",
            "bid_price": 98.0,
            "offer_price": 98.015625,
            "mid_price": 98.0078125,
            "eod_price": 98.0,
            "bid_yield": 2.968818189957474,
            "offer_yield": 2.966099979838817,
            "eod_yield": 2.968818189957474
        },
        {
            "cusip": "912828KT6",
            "bid_price": 96.3125,
            "offer_price": 96.328125,
            "mid_price": 96.3203125,
            "eod_price": 96.34375,
            "bid_yield": 3.002212972896574,
            "offer_yield": 2.999498281583166,
            "eod_yield": 2.9967840873155227
        },
        {
            "cusip": "912828KR0",
            "bid_price": 97.6875,
            "offer_price": 97.703125,
            "mid_price": 97.6953125,
            "eod_price": 97.6875,
            "bid_yield": 3.013831549532139,
            "offer_yield": 3.0111678979676806,
            "eod_yield": 3.013831549532139
        },
        {
            "cusip": "912828FF2",
            "bid_price": 113.09375,
            "offer_price": 113.125,
            "mid_price": 113.109375,
            "eod_price": 113.125,
            "bid_yield": 2.9396797153143313,
            "offer_yield": 2.934829403571829,
            "eod_yield": 2.934829403571829
        },
        {
            "cusip": "912828FF2",
            "bid_price": 113.09375,
            "offer_price": 113.125,
            "mid_price": 113.109375,
            "eod_price": 113.125,
            "bid_yield": 2.9396797153143313,
            "offer_yield": 2.934829403571829,
            "eod_yield": 2.934829403571829
        },
        {
            "cusip": "912828KW9",
            "bid_price": 101.46875,
            "offer_price": 101.5,
            "mid_price": 101.484375,
            "eod_price": 101.5,
            "bid_yield": 3.0053177950430077,
            "offer_yield": 3.0001665031775606,
            "eod_yield": 3.0001665031775606
        },
        {
            "cusip": "912828KZ2",
            "bid_price": 101.375,
            "offer_price": 101.390625,
            "mid_price": 101.3828125,
            "eod_price": 101.40625,
            "bid_yield": 3.0232294264321924,
            "offer_yield": 3.0206788598712078,
            "eod_yield": 3.018128743201958
        },
        {
            "cusip": "912828LD0",
            "bid_price": 101.25,
            "offer_price": 101.265625,
            "mid_price": 101.2578125,
            "eod_price": 101.28125,
            "bid_yield": 3.0460337017717327,
            "offer_yield": 3.043507978628167,
            "eod_yield": 3.040982701589103
        },
        {
            "cusip": "912828FQ8",
            "bid_price": 111.4375,
            "offer_price": 111.453125,
            "mid_price": 111.4453125,
            "eod_price": 111.46875,
            "bid_yield": 3.0234261734906305,
            "offer_yield": 3.021052858872677,
            "eod_yield": 3.0186799344366526
        },
        {
            "cusip": "912828FQ8",
            "bid_price": 111.4375,
            "offer_price": 111.453125,
            "mid_price": 111.4453125,
            "eod_price": 111.46875,
            "bid_yield": 3.0234261734906305,
            "offer_yield": 3.021052858872677,
            "eod_yield": 3.0186799344366526
        },
        {
            "cusip": "912828LL2",
            "bid_price": 99.46875,
            "offer_price": 99.484375,
            "mid_price": 99.4765625,
            "eod_price": 99.5,
            "bid_yield": 3.0854809987207448,
            "offer_yield": 3.082953346913892,
            "eod_yield": 3.0804261477644905
        },
        {
            "cusip": "912828FY1",
            "bid_price": 109.75,
            "offer_price": 109.765625,
            "mid_price": 109.7578125,
            "eod_price": 109.78125,
            "bid_yield": 3.092355397881452,
            "offer_yield": 3.0900302977882506,
            "eod_yield": 3.0877055848195023
        },
        {
            "cusip": "912828FY1",
            "bid_price": 109.75,
            "offer_price": 109.765625,
            "mid_price": 109.7578125,
            "eod_price": 109.78125,
            "bid_yield": 3.092355397881452,
            "offer_yield": 3.0900302977882506,
            "eod_yield": 3.0877055848195023
        },
        {
            "cusip": "912828GH7",
            "bid_price": 109.65625,
            "offer_price": 109.6875,
            "mid_price": 109.671875,
            "eod_price": 109.71875,
            "bid_yield": 3.1499049665077514,
            "offer_yield": 3.145383938539221,
            "eod_yield": 3.140864418625181
        },
        {
            "cusip": "912828GH7",
            "bid_price": 109.65625,
            "offer_price": 109.6875,
            "mid_price": 109.671875,
            "eod_price": 109.71875,
            "bid_yield": 3.1499049665077514,
            "offer_yield": 3.145383938539221,
            "eod_yield": 3.140864418625181
        },
        {
            "cusip": "912828GS3",
            "bid_price": 108.71875,
            "offer_price": 108.734375,
            "mid_price": 108.7265625,
            "eod_price": 108.78125,
            "bid_yield": 3.2040187691057684,
            "offer_yield": 3.201808194816521,
            "eod_yield": 3.1951787013961246
        },
        {
            "cusip": "912828GS3",
            "bid_price": 108.71875,
            "offer_price": 108.734375,
            "mid_price": 108.7265625,
            "eod_price": 108.78125,
            "bid_yield": 3.2040187691057684,
            "offer_yield": 3.201808194816521,
            "eod_yield": 3.1951787013961246
        },
        {
            "cusip": "912828HA1",
            "bid_price": 110.3125,
            "offer_price": 110.34375,
            "mid_price": 110.328125,
            "eod_price": 110.40625,
            "bid_yield": 3.2570290285380055,
            "offer_yield": 3.2527603154097817,
            "eod_yield": 3.244227153004554
        },
        {
            "cusip": "912828HA1",
            "bid_price": 110.3125,
            "offer_price": 110.34375,
            "mid_price": 110.328125,
            "eod_price": 110.40625,
            "bid_yield": 3.2570290285380055,
            "offer_yield": 3.2527603154097817,
            "eod_yield": 3.244227153004554
        },
        {
            "cusip": "912828HH6",
            "bid_price": 106.65625,
            "offer_price": 106.671875,
            "mid_price": 106.6640625,
            "eod_price": 106.71875,
            "bid_yield": 3.3100972277314575,
            "offer_yield": 3.3079738470106186,
            "eod_yield": 3.3016058846022895
        },
        {
            "cusip": "912828HH6",
            "bid_price": 106.65625,
            "offer_price": 106.671875,
            "mid_price": 106.6640625,
            "eod_price": 106.71875,
            "bid_yield": 3.3100972277314575,
            "offer_yield": 3.3079738470106186,
            "eod_yield": 3.3016058846022895
        },
        {
            "cusip": "912828HR4",
            "bid_price": 100.96875,
            "offer_price": 100.984375,
            "mid_price": 100.9765625,
            "eod_price": 101.03125,
            "bid_yield": 3.3661773190282323,
            "offer_yield": 3.364036784167655,
            "eod_yield": 3.3576174733680597
        },
        {
            "cusip": "912828HR4",
            "bid_price": 100.96875,
            "offer_price": 100.984375,
            "mid_price": 100.9765625,
            "eod_price": 101.03125,
            "bid_yield": 3.3661773190282323,
            "offer_yield": 3.364036784167655,
            "eod_yield": 3.3576174733680597
        },
        {
            "cusip": "912828HR4",
            "bid_price": 100.96875,
            "offer_price": 100.984375,
            "mid_price": 100.9765625,
            "eod_price": 101.03125,
            "bid_yield": 3.3661773190282323,
            "offer_yield": 3.364036784167655,
            "eod_yield": 3.3576174733680597
        },
        {
            "cusip": "912828HZ6",
            "bid_price": 103.65625,
            "offer_price": 103.671875,
            "mid_price": 103.6640625,
            "eod_price": 103.75,
            "bid_yield": 3.3830446036839064,
            "offer_yield": 3.3809879848881352,
            "eod_yield": 3.3707102993960776
        },
        {
            "cusip": "912828HZ6",
            "bid_price": 103.65625,
            "offer_price": 103.671875,
            "mid_price": 103.6640625,
            "eod_price": 103.75,
            "bid_yield": 3.3830446036839064,
            "offer_yield": 3.3809879848881352,
            "eod_yield": 3.3707102993960776
        },
        {
            "cusip": "912828JH4",
            "bid_price": 104.34375,
            "offer_price": 104.359375,
            "mid_price": 104.3515625,
            "eod_price": 104.46875,
            "bid_yield": 3.4286928559018937,
            "offer_yield": 3.4266898779636126,
            "eod_yield": 3.4126788347197277
        },
        {
            "cusip": "912828JH4",
            "bid_price": 104.34375,
            "offer_price": 104.359375,
            "mid_price": 104.3515625,
            "eod_price": 104.46875,
            "bid_yield": 3.4286928559018937,
            "offer_yield": 3.4266898779636126,
            "eod_yield": 3.4126788347197277
        },
        {
            "cusip": "912828JR2",
            "bid_price": 102.28125,
            "offer_price": 102.296875,
            "mid_price": 102.2890625,
            "eod_price": 102.375,
            "bid_yield": 3.4563970635603636,
            "offer_yield": 3.4544155821486853,
            "eod_yield": 3.4445134584159063
        },
        {
            "cusip": "912828JR2",
            "bid_price": 102.28125,
            "offer_price": 102.296875,
            "mid_price": 102.2890625,
            "eod_price": 102.375,
            "bid_yield": 3.4563970635603636,
            "offer_yield": 3.4544155821486853,
            "eod_yield": 3.4445134584159063
        },
        {
            "cusip": "912828JR2",
            "bid_price": 102.28125,
            "offer_price": 102.296875,
            "mid_price": 102.2890625,
            "eod_price": 102.375,
            "bid_yield": 3.4563970635603636,
            "offer_yield": 3.4544155821486853,
            "eod_yield": 3.4445134584159063
        },
        {
            "cusip": "912828KD1",
            "bid_price": 94.25,
            "offer_price": 94.265625,
            "mid_price": 94.2578125,
            "eod_price": 94.375,
            "bid_yield": 3.4725212335683824,
            "offer_yield": 3.4704897884385137,
            "eod_yield": 3.4562804276258077
        },
        {
            "cusip": "912828KD1",
            "bid_price": 94.25,
            "offer_price": 94.265625,
            "mid_price": 94.2578125,
            "eod_price": 94.375,
            "bid_yield": 3.4725212335683824,
            "offer_yield": 3.4704897884385137,
            "eod_yield": 3.4562804276258077
        },
        {
            "cusip": "912828KD1",
            "bid_price": 94.25,
            "offer_price": 94.265625,
            "mid_price": 94.2578125,
            "eod_price": 94.375,
            "bid_yield": 3.4725212335683824,
            "offer_yield": 3.4704897884385137,
            "eod_yield": 3.4562804276258077
        },
        {
            "cusip": "912828KQ2",
            "bid_price": 97.21875,
            "offer_price": 97.21875,
            "mid_price": 97.21875,
            "eod_price": 97.3125,
            "bid_yield": 3.4668069936782033,
            "offer_yield": 3.4668069936782033,
            "eod_yield": 3.455102019077241
        },
        {
            "cusip": "912828KQ2",
            "bid_price": 97.21875,
            "offer_price": 97.21875,
            "mid_price": 97.21875,
            "eod_price": 97.3125,
            "bid_yield": 3.466652811034794,
            "offer_yield": 3.466652811034794,
            "eod_yield": 3.4549485219328404
        },
        {
            "cusip": "912828KQ2",
            "bid_price": 97.21875,
            "offer_price": 97.21875,
            "mid_price": 97.21875,
            "eod_price": 97.3125,
            "bid_yield": 3.4664935055887973,
            "offer_yield": 3.4664935055887973,
            "eod_yield": 3.4547899247370473
        },
        {
            "cusip": "912828LJ7",
            "bid_price": 101.375,
            "offer_price": 101.375,
            "mid_price": 101.375,
            "eod_price": 101.46875,
            "bid_yield": 3.460303419246036,
            "offer_yield": 3.460303419246036,
            "eod_yield": 3.4491230931893817
        },
        {
            "cusip": "912828LJ7",
            "bid_price": 101.375,
            "offer_price": 101.375,
            "mid_price": 101.375,
            "eod_price": 101.46875,
            "bid_yield": 3.459833289462208,
            "offer_yield": 3.459833289462208,
            "eod_yield": 3.4486549645438687
        },
        {
            "cusip": "912828LJ7",
            "bid_price": 101.375,
            "offer_price": 101.375,
            "mid_price": 101.375,
            "eod_price": 101.46875,
            "bid_yield": 3.459378970499384,
            "offer_yield": 3.459378970499384,
            "eod_yield": 3.448202579218749
        },
        {
            "cusip": "912810DN5",
            "bid_price": 101.65625,
            "offer_price": 0.0,
            "mid_price": 50.828125,
            "eod_price": 101.65625,
            "bid_yield": 11.307799853710733,
            "offer_yield": 1020.3674229428143,
            "eod_yield": 11.307799853710733
        },
        {
            "cusip": "912810DP0",
            "bid_price": 143.375,
            "offer_price": 143.4375,
            "mid_price": 143.40625,
            "eod_price": 143.375,
            "bid_yield": 2.5793658615357806,
            "offer_yield": 2.569353848793956,
            "eod_yield": 2.5793658615357806
        },
        {
            "cusip": "912810DP0",
            "bid_price": 143.375,
            "offer_price": 143.4375,
            "mid_price": 143.40625,
            "eod_price": 143.375,
            "bid_yield": 2.5793658615357806,
            "offer_yield": 2.569353848793956,
            "eod_yield": 2.5793658615357806
        },
        {
            "cusip": "912810DS4",
            "bid_price": 142.65625,
            "offer_price": 142.71875,
            "mid_price": 142.6875,
            "eod_price": 142.65625,
            "bid_yield": 2.735040641845762,
            "offer_yield": 2.725744681028355,
            "eod_yield": 2.735040641845762
        },
        {
            "cusip": "912810DT2",
            "bid_price": 139.5625,
            "offer_price": 139.640625,
            "mid_price": 139.6015625,
            "eod_price": 139.59375,
            "bid_yield": 2.8139539420052735,
            "offer_yield": 2.8025827987056715,
            "eod_yield": 2.809404545167918
        },
        {
            "cusip": "912810DV7",
            "bid_price": 136.8125,
            "offer_price": 136.890625,
            "mid_price": 136.8515625,
            "eod_price": 136.875,
            "bid_yield": 2.897887733771428,
            "offer_yield": 2.8867521457078054,
            "eod_yield": 2.888978639877104
        },
        {
            "cusip": "912810DW5",
            "bid_price": 125.625,
            "offer_price": 125.65625,
            "mid_price": 125.640625,
            "eod_price": 125.625,
            "bid_yield": 2.9692550037625147,
            "offer_yield": 2.9647028046306456,
            "eod_yield": 2.9692550037625147
        },
        {
            "cusip": "912810DW5",
            "bid_price": 125.625,
            "offer_price": 125.65625,
            "mid_price": 125.640625,
            "eod_price": 125.625,
            "bid_yield": 2.9692550037625147,
            "offer_yield": 2.9647028046306456,
            "eod_yield": 2.9692550037625147
        },
        {
            "cusip": "912810DX3",
            "bid_price": 127.875,
            "offer_price": 127.90625,
            "mid_price": 127.890625,
            "eod_price": 127.9375,
            "bid_yield": 3.11525439024932,
            "offer_yield": 3.111016877972107,
            "eod_yield": 3.1067806202059667
        },
        {
            "cusip": "912810DX3",
            "bid_price": 127.875,
            "offer_price": 127.90625,
            "mid_price": 127.890625,
            "eod_price": 127.9375,
            "bid_yield": 3.11525439024932,
            "offer_yield": 3.111016877972107,
            "eod_yield": 3.1067806202059667
        },
        {
            "cusip": "912810DY1",
            "bid_price": 137.28125,
            "offer_price": 137.328125,
            "mid_price": 137.3046875,
            "eod_price": 137.375,
            "bid_yield": 3.208665935150576,
            "offer_yield": 3.202928758070428,
            "eod_yield": 3.197193992581808
        },
        {
            "cusip": "912810DY1",
            "bid_price": 137.28125,
            "offer_price": 137.328125,
            "mid_price": 137.3046875,
            "eod_price": 137.375,
            "bid_yield": 3.208665935150576,
            "offer_yield": 3.202928758070428,
            "eod_yield": 3.197193992581808
        },
        {
            "cusip": "912810DZ8",
            "bid_price": 138.8125,
            "offer_price": 138.859375,
            "mid_price": 138.8359375,
            "eod_price": 138.90625,
            "bid_yield": 3.2569185968767393,
            "offer_yield": 3.2513726246236763,
            "eod_yield": 3.2458289656583372
        },
        {
            "cusip": "912810DZ8",
            "bid_price": 138.8125,
            "offer_price": 138.859375,
            "mid_price": 138.8359375,
            "eod_price": 138.90625,
            "bid_yield": 3.2569185968767393,
            "offer_yield": 3.2513726246236763,
            "eod_yield": 3.2458289656583372
        },
        {
            "cusip": "912810EA2",
            "bid_price": 143.25,
            "offer_price": 143.296875,
            "mid_price": 143.2734375,
            "eod_price": 143.34375,
            "bid_yield": 3.3244559903676527,
            "offer_yield": 3.3194262851160965,
            "eod_yield": 3.314398630073348
        },
        {
            "cusip": "912810EB0",
            "bid_price": 143.4375,
            "offer_price": 143.484375,
            "mid_price": 143.4609375,
            "eod_price": 143.5625,
            "bid_yield": 3.424485507290935,
            "offer_yield": 3.4196802535521025,
            "eod_yield": 3.4116758591497174
        },
        {
            "cusip": "912810EC8",
            "bid_price": 143.15625,
            "offer_price": 143.21875,
            "mid_price": 143.1875,
            "eod_price": 143.25,
            "bid_yield": 3.454073177172691,
            "offer_yield": 3.4477974060162504,
            "eod_yield": 3.444660806377263
        },
        {
            "cusip": "912810EC8",
            "bid_price": 143.15625,
            "offer_price": 143.21875,
            "mid_price": 143.1875,
            "eod_price": 143.25,
            "bid_yield": 3.454073177172691,
            "offer_yield": 3.4477974060162504,
            "eod_yield": 3.444660806377263
        },
        {
            "cusip": "912810ED6",
            "bid_price": 137.9375,
            "offer_price": 138.0,
            "mid_price": 137.96875,
            "eod_price": 138.0625,
            "bid_yield": 3.543868744888519,
            "offer_yield": 3.537691589166585,
            "eod_yield": 3.5315179257145792
        },
        {
            "cusip": "912810ED6",
            "bid_price": 137.9375,
            "offer_price": 138.0,
            "mid_price": 137.96875,
            "eod_price": 138.0625,
            "bid_yield": 3.543868744888519,
            "offer_yield": 3.537691589166585,
            "eod_yield": 3.5315179257145792
        },
        {
            "cusip": "912810EE4",
            "bid_price": 141.96875,
            "offer_price": 142.03125,
            "mid_price": 142.0,
            "eod_price": 142.09375,
            "bid_yield": 3.617790321334031,
            "offer_yield": 3.6119574499090965,
            "eod_yield": 3.606127811217685
        },
        {
            "cusip": "912810EF1",
            "bid_price": 144.53125,
            "offer_price": 144.59375,
            "mid_price": 144.5625,
            "eod_price": 144.65625,
            "bid_yield": 3.6591580430678614,
            "offer_yield": 3.6534976827568,
            "eod_yield": 3.6478404195890897
        },
        {
            "cusip": "912810EG9",
            "bid_price": 144.96875,
            "offer_price": 145.03125,
            "mid_price": 145.0,
            "eod_price": 145.0625,
            "bid_yield": 3.696168124890471,
            "offer_yield": 3.690617629000519,
            "eod_yield": 3.687843519675331
        },
        {
            "cusip": "912810EG9",
            "bid_price": 144.96875,
            "offer_price": 145.03125,
            "mid_price": 145.0,
            "eod_price": 145.0625,
            "bid_yield": 3.696168124890471,
            "offer_yield": 3.690617629000519,
            "eod_yield": 3.687843519675331
        },
        {
            "cusip": "912810EH7",
            "bid_price": 137.65625,
            "offer_price": 137.734375,
            "mid_price": 137.6953125,
            "eod_price": 137.78125,
            "bid_yield": 3.776179328557544,
            "offer_yield": 3.769230733892866,
            "eod_yield": 3.7650639682411966
        },
        {
            "cusip": "912810EJ3",
            "bid_price": 140.21875,
            "offer_price": 140.296875,
            "mid_price": 140.2578125,
            "eod_price": 140.34375,
            "bid_yield": 3.8135823184477817,
            "offer_yield": 3.8068270923171337,
            "eod_yield": 3.802776251063242
        },
        {
            "cusip": "912810EK0",
            "bid_price": 140.59375,
            "offer_price": 140.65625,
            "mid_price": 140.625,
            "eod_price": 140.6875,
            "bid_yield": 3.839960938539775,
            "offer_yield": 3.8346509942907545,
            "eod_yield": 3.8319971494936897
        },
        {
            "cusip": "912810EL8",
            "bid_price": 139.71875,
            "offer_price": 139.796875,
            "mid_price": 139.7578125,
            "eod_price": 139.8125,
            "bid_yield": 3.868635304482494,
            "offer_yield": 3.8620717937048057,
            "eod_yield": 3.8607596530250263
        },
        {
            "cusip": "912810EL8",
            "bid_price": 139.71875,
            "offer_price": 139.796875,
            "mid_price": 139.7578125,
            "eod_price": 139.8125,
            "bid_yield": 3.868635304482494,
            "offer_yield": 3.8620717937048057,
            "eod_yield": 3.8607596530250263
        },
        {
            "cusip": "912810EL8",
            "bid_price": 139.71875,
            "offer_price": 139.796875,
            "mid_price": 139.7578125,
            "eod_price": 139.8125,
            "bid_yield": 3.868635304482494,
            "offer_yield": 3.8620717937048057,
            "eod_yield": 3.8607596530250263
        },
        {
            "cusip": "912810EM6",
            "bid_price": 132.9375,
            "offer_price": 133.015625,
            "mid_price": 132.9765625,
            "eod_price": 133.0625,
            "bid_yield": 3.9619134338366564,
            "offer_yield": 3.9554103323673373,
            "eod_yield": 3.951510807267493
        },
        {
            "cusip": "912810EN4",
            "bid_price": 137.03125,
            "offer_price": 137.109375,
            "mid_price": 137.0703125,
            "eod_price": 137.1875,
            "bid_yield": 3.9784707075334915,
            "offer_yield": 3.9721885858777437,
            "eod_yield": 3.965911055972434
        },
        {
            "cusip": "912810EP9",
            "bid_price": 131.96875,
            "offer_price": 132.046875,
            "mid_price": 132.0078125,
            "eod_price": 132.15625,
            "bid_yield": 4.0148410855883485,
            "offer_yield": 4.008478574239573,
            "eod_yield": 3.9995791414589497
        },
        {
            "cusip": "912810EP9",
            "bid_price": 131.96875,
            "offer_price": 132.046875,
            "mid_price": 132.0078125,
            "eod_price": 132.15625,
            "bid_yield": 4.0148410855883485,
            "offer_yield": 4.008478574239573,
            "eod_yield": 3.9995791414589497
        },
        {
            "cusip": "912810EQ7",
            "bid_price": 123.25,
            "offer_price": 123.3125,
            "mid_price": 123.28125,
            "eod_price": 123.34375,
            "bid_yield": 4.045273684026604,
            "offer_yield": 4.040085864391409,
            "eod_yield": 4.037493206302259
        },
        {
            "cusip": "912810EQ7",
            "bid_price": 123.25,
            "offer_price": 123.3125,
            "mid_price": 123.28125,
            "eod_price": 123.34375,
            "bid_yield": 4.045273684026604,
            "offer_yield": 4.040085864391409,
            "eod_yield": 4.037493206302259
        },
        {
            "cusip": "912810ES3",
            "bid_price": 138.40625,
            "offer_price": 138.453125,
            "mid_price": 138.4296875,
            "eod_price": 138.53125,
            "bid_yield": 4.0752757600220475,
            "offer_yield": 4.071898052195392,
            "eod_yield": 4.066271857376105
        },
        {
            "cusip": "912810ET1",
            "bid_price": 140.09375,
            "offer_price": 140.15625,
            "mid_price": 140.125,
            "eod_price": 140.21875,
            "bid_yield": 4.088708483971743,
            "offer_yield": 4.08429343376031,
            "eod_yield": 4.079880964723652
        },
        {
            "cusip": "912810EV6",
            "bid_price": 132.125,
            "offer_price": 132.1875,
            "mid_price": 132.15625,
            "eod_price": 132.21875,
            "bid_yield": 4.102855257448169,
            "offer_yield": 4.098362016031455,
            "eod_yield": 4.096116435135096
        },
        {
            "cusip": "912810EW4",
            "bid_price": 121.9375,
            "offer_price": 122.0,
            "mid_price": 121.96875,
            "eod_price": 121.96875,
            "bid_yield": 4.142487057957211,
            "offer_yield": 4.13783626498653,
            "eod_yield": 4.140161275491846
        },
        {
            "cusip": "912810EX2",
            "bid_price": 131.40625,
            "offer_price": 131.46875,
            "mid_price": 131.4375,
            "eod_price": 131.46875,
            "bid_yield": 4.145434347904279,
            "offer_yield": 4.141107522530534,
            "eod_yield": 4.141107522530534
        },
        {
            "cusip": "912810EY0",
            "bid_price": 128.59375,
            "offer_price": 128.65625,
            "mid_price": 128.625,
            "eod_price": 128.6875,
            "bid_yield": 4.151440452267019,
            "offer_yield": 4.147092992518128,
            "eod_yield": 4.144920303362738
        },
        {
            "cusip": "912810EZ7",
            "bid_price": 130.28125,
            "offer_price": 130.34375,
            "mid_price": 130.3125,
            "eod_price": 130.375,
            "bid_yield": 4.160778679050969,
            "offer_yield": 4.156511237212501,
            "eod_yield": 4.154378528831876
        },
        {
            "cusip": "912810FA1",
            "bid_price": 127.65625,
            "offer_price": 127.71875,
            "mid_price": 127.6875,
            "eod_price": 127.8125,
            "bid_yield": 4.166377371627258,
            "offer_yield": 4.162133516113786,
            "eod_yield": 4.15577287414311
        },
        {
            "cusip": "912810FB9",
            "bid_price": 124.65625,
            "offer_price": 124.734375,
            "mid_price": 124.6953125,
            "eod_price": 124.84375,
            "bid_yield": 4.173119170147647,
            "offer_yield": 4.167776824465681,
            "eod_yield": 4.16030495168246
        },
        {
            "cusip": "912810FB9",
            "bid_price": 124.65625,
            "offer_price": 124.734375,
            "mid_price": 124.6953125,
            "eod_price": 124.84375,
            "bid_yield": 4.173119170147647,
            "offer_yield": 4.167776824465681,
            "eod_yield": 4.16030495168246
        },
        {
            "cusip": "912810FE3",
            "bid_price": 116.96875,
            "offer_price": 117.046875,
            "mid_price": 117.0078125,
            "eod_price": 117.21875,
            "bid_yield": 4.1905212831339735,
            "offer_yield": 4.1850878746242515,
            "eod_yield": 4.173151147452905
        },
        {
            "cusip": "912810FF0",
            "bid_price": 113.8125,
            "offer_price": 113.890625,
            "mid_price": 113.8515625,
            "eod_price": 114.0625,
            "bid_yield": 4.192921595870844,
            "offer_yield": 4.187434980409279,
            "eod_yield": 4.175381792843804
        },
        {
            "cusip": "912810FG8",
            "bid_price": 113.75,
            "offer_price": 113.84375,
            "mid_price": 113.796875,
            "eod_price": 114.03125,
            "bid_yield": 4.205532654429501,
            "offer_yield": 4.1989968345039115,
            "eod_yield": 4.1859464122626076
        },
        {
            "cusip": "912810FJ2",
            "bid_price": 125.875,
            "offer_price": 125.96875,
            "mid_price": 125.921875,
            "eod_price": 126.21875,
            "bid_yield": 4.193793361251119,
            "offer_yield": 4.187803678783147,
            "eod_yield": 4.171860351034011
        },
        {
            "cusip": "912810FM5",
            "bid_price": 128.21875,
            "offer_price": 128.3125,
            "mid_price": 128.265625,
            "eod_price": 128.59375,
            "bid_yield": 4.1930769376233386,
            "offer_yield": 4.187308358679151,
            "eod_yield": 4.1700367252305295
        },
        {
            "cusip": "912810FM5",
            "bid_price": 128.21875,
            "offer_price": 128.3125,
            "mid_price": 128.265625,
            "eod_price": 128.59375,
            "bid_yield": 4.1930769376233386,
            "offer_yield": 4.187308358679151,
            "eod_yield": 4.1700367252305295
        },
        {
            "cusip": "912810FP8",
            "bid_price": 116.25,
            "offer_price": 116.34375,
            "mid_price": 116.296875,
            "eod_price": 116.625,
            "bid_yield": 4.214361922220784,
            "offer_yield": 4.208316365805946,
            "eod_yield": 4.190218852019826
        },
        {
            "cusip": "912810FP8",
            "bid_price": 116.25,
            "offer_price": 116.34375,
            "mid_price": 116.296875,
            "eod_price": 116.625,
            "bid_yield": 4.214361922220784,
            "offer_yield": 4.208316365805946,
            "eod_yield": 4.190218852019826
        },
        {
            "cusip": "912810FT0",
            "bid_price": 104.375,
            "offer_price": 104.453125,
            "mid_price": 104.4140625,
            "eod_price": 104.9375,
            "bid_yield": 4.22319913982494,
            "offer_yield": 4.218407375608686,
            "eod_yield": 4.1888082452244895
        },
        {
            "cusip": "912810FT0",
            "bid_price": 104.375,
            "offer_price": 104.453125,
            "mid_price": 104.4140625,
            "eod_price": 104.9375,
            "bid_yield": 4.22319913982494,
            "offer_yield": 4.218407375608686,
            "eod_yield": 4.1888082452244895
        },
        {
            "cusip": "912810PT9",
            "bid_price": 108.46875,
            "offer_price": 108.546875,
            "mid_price": 108.5078125,
            "eod_price": 109.0,
            "bid_yield": 4.224983098646294,
            "offer_yield": 4.220412504244513,
            "eod_yield": 4.193993304761721
        },
        {
            "cusip": "912810PT9",
            "bid_price": 108.46875,
            "offer_price": 108.546875,
            "mid_price": 108.5078125,
            "eod_price": 109.0,
            "bid_yield": 4.224983098646294,
            "offer_yield": 4.220412504244513,
            "eod_yield": 4.193993304761721
        },
        {
            "cusip": "912810PU6",
            "bid_price": 112.59375,
            "offer_price": 112.6875,
            "mid_price": 112.640625,
            "eod_price": 113.1875,
            "bid_yield": 4.223236824372283,
            "offer_yield": 4.217924148370301,
            "eod_yield": 4.189694342571263
        },
        {
            "cusip": "912810PU6",
            "bid_price": 112.59375,
            "offer_price": 112.6875,
            "mid_price": 112.640625,
            "eod_price": 113.1875,
            "bid_yield": 4.223236824372283,
            "offer_yield": 4.217924148370301,
            "eod_yield": 4.189694342571263
        },
        {
            "cusip": "912810PW2",
            "bid_price": 102.40625,
            "offer_price": 102.484375,
            "mid_price": 102.4453125,
            "eod_price": 102.9375,
            "bid_yield": 4.228401375915271,
            "offer_yield": 4.223730596799262,
            "eod_yield": 4.196737847208083
        },
        {
            "cusip": "912810PW2",
            "bid_price": 102.40625,
            "offer_price": 102.484375,
            "mid_price": 102.4453125,
            "eod_price": 102.9375,
            "bid_yield": 4.228401375915271,
            "offer_yield": 4.223730596799262,
            "eod_yield": 4.196737847208083
        },
        {
            "cusip": "912810PX0",
            "bid_price": 104.625,
            "offer_price": 104.6875,
            "mid_price": 104.65625,
            "eod_price": 105.09375,
            "bid_yield": 4.219942791802179,
            "offer_yield": 4.2162822602983026,
            "eod_yield": 4.192563320413145
        },
        {
            "cusip": "912810PX0",
            "bid_price": 104.625,
            "offer_price": 104.6875,
            "mid_price": 104.65625,
            "eod_price": 105.09375,
            "bid_yield": 4.219942791802179,
            "offer_yield": 4.2162822602983026,
            "eod_yield": 4.192563320413145
        },
        {
            "cusip": "912810QA9",
            "bid_price": 87.875,
            "offer_price": 87.921875,
            "mid_price": 87.8984375,
            "eod_price": 88.3125,
            "bid_yield": 4.223928224818252,
            "offer_yield": 4.220869532985202,
            "eod_yield": 4.195467638453307
        },
        {
            "cusip": "912810QA9",
            "bid_price": 87.875,
            "offer_price": 87.921875,
            "mid_price": 87.8984375,
            "eod_price": 88.3125,
            "bid_yield": 4.223928224818252,
            "offer_yield": 4.220869532985202,
            "eod_yield": 4.195467638453307
        },
        {
            "cusip": "912810QB7",
            "bid_price": 100.4375,
            "offer_price": 100.484375,
            "mid_price": 100.4609375,
            "eod_price": 100.90625,
            "bid_yield": 4.223962596028492,
            "offer_yield": 4.221184660469976,
            "eod_yield": 4.196265070856933
        },
        {
            "cusip": "912810QB7",
            "bid_price": 100.4375,
            "offer_price": 100.484375,
            "mid_price": 100.4609375,
            "eod_price": 100.90625,
            "bid_yield": 4.223841643525496,
            "offer_yield": 4.2210638658580315,
            "eod_yield": 4.196145686046823
        },
        {
            "cusip": "912810QB7",
            "bid_price": 100.4375,
            "offer_price": 100.484375,
            "mid_price": 100.4609375,
            "eod_price": 100.90625,
            "bid_yield": 4.223716670087525,
            "offer_yield": 4.220939055550944,
            "eod_yield": 4.196022332329404
        },
        {
            "cusip": "912810QC5",
            "bid_price": 104.625,
            "offer_price": 104.640625,
            "mid_price": 104.6328125,
            "eod_price": 105.0625,
            "bid_yield": 4.226531631145536,
            "offer_yield": 4.225635316487039,
            "eod_yield": 4.201506337506733
        },
        {
            "cusip": "912810QC5",
            "bid_price": 104.625,
            "offer_price": 104.640625,
            "mid_price": 104.6328125,
            "eod_price": 105.0625,
            "bid_yield": 4.226190028523932,
            "offer_yield": 4.225293857306165,
            "eod_yield": 4.201168723715853
        },
        {
            "cusip": "912810QC5",
            "bid_price": 104.625,
            "offer_price": 104.640625,
            "mid_price": 104.6328125,
            "eod_price": 105.0625,
            "bid_yield": 4.225859890377268,
            "offer_yield": 4.224963857765433,
            "eod_yield": 4.200842439959986
        }
    ]
}